{"subjectCode":"CAH","courseCode":"CAH3548","courseTitle":"Critical Approaches to Cultural Heritage","creditUnits":"3","courseLevel":["B"],"sections":{"A":{"restrictions":["only for Major: CHIS","only for Stream: CUH"],"activities":[{"crn":"11508","day":2,"startTime":"12:00","endTime":"14:50","bldg":"YEUNG","room":"Y5-203","section":"CA1","web":false}]},"B":{"restrictions":["only for Major: CHIS","only for Stream: HCH"],"activities":[{"crn":"13649","day":2,"startTime":"12:00","endTime":"14:50","bldg":"YEUNG","room":"Y5-203","section":"CB1","web":true}]}}}