{"subjectCode":"LW","courseCode":"LW5658","courseTitle":"Commercial Law","creditUnits":"3","courseLevel":["P"],"sections":{"0":{"restrictions":["only for Programme: JD4"],"activities":[{"crn":"10275","day":2,"startTime":"10:00","endTime":"11:50","bldg":"LI","room":"3508","section":"C01","web":true},{"crn":"10276","day":2,"startTime":"13:00","endTime":"13:50","bldg":"LAU","room":"6-211","section":"T01","web":true},{"crn":"10277","day":3,"startTime":"13:00","endTime":"13:50","bldg":"LAU","room":"6-211","section":"T02","web":true},{"crn":"10500","day":3,"startTime":"14:00","endTime":"14:50","bldg":"LAU","room":"6-211","section":"T03","web":true}]}}}