{"subjectCode":"LW","courseCode":"LW5656","courseTitle":"Company Law I","creditUnits":"3","courseLevel":["P"],"sections":{"0":{"restrictions":["only for Programme: JD4"],"activities":[{"crn":"10099","day":4,"startTime":"10:00","endTime":"11:50","bldg":"YEUNG","room":"LT-18","section":"C01","web":true},{"crn":"10497","day":1,"startTime":"14:00","endTime":"14:50","bldg":"LI","room":"2413","section":"T01","web":true},{"crn":"10498","day":1,"startTime":"15:00","endTime":"15:50","bldg":"LI","room":"1402","section":"T02","web":true},{"crn":"10499","day":1,"startTime":"13:00","endTime":"13:50","bldg":"LI","room":"1402","section":"T03","web":true}]}}}