{"subjectCode":"MNE","courseCode":"MNE4010","courseTitle":"Dynamics and Vibrations","creditUnits":"3","courseLevel":["B"],"sections":{"0":{"restrictions":["only for Major: M.E., NRE"],"activities":[{"crn":"12243","day":1,"startTime":"14:00","endTime":"16:50","bldg":"YEUNG","room":"B5-211","section":"C01","web":true},{"crn":"12244","day":2,"startTime":"09:00","endTime":"11:50","bldg":"LI","room":"6502","section":"L01","web":true},{"crn":"12244","day":2,"startTime":"09:00","endTime":"11:50","bldg":"LI","room":"6502","section":"L01","web":true},{"crn":"12254","day":2,"startTime":"09:00","endTime":"11:50","bldg":"LI","room":"6502","section":"L02","web":true},{"crn":"12254","day":2,"startTime":"09:00","endTime":"11:50","bldg":"LI","room":"6502","section":"L02","web":true},{"crn":"12255","day":3,"startTime":"14:00","endTime":"16:50","bldg":"LI","room":"6502","section":"L03","web":true},{"crn":"12255","day":3,"startTime":"14:00","endTime":"16:50","bldg":"LI","room":"6502","section":"L03","web":true}]}}}