{"subjectCode":"PIA","courseCode":"PIA5509","courseTitle":"The Urban Management Workshop: Exploring the Contemporary City","creditUnits":"3","courseLevel":["P"],"sections":{"X":{"restrictions":["only for Programme: MAHUM"],"activities":[{"crn":"12625","day":3,"startTime":"19:00","endTime":"21:50","bldg":"LI","room":"3614","section":"CX1","web":false}]},"Y":{"restrictions":["only for Programme: MAPPM"],"activities":[{"crn":"13443","day":3,"startTime":"19:00","endTime":"21:50","bldg":"LI","room":"3614","section":"CY1","web":false}]}}}