{"subjectCode":"SG","courseCode":"SG8002","courseTitle":"English for the Medium of Instruction","creditUnits":"1","courseLevel":["R"],"sections":{"0":{"restrictions":["only for College: CB, CH, FL, SM"],"activities":[{"crn":"10767","day":5,"startTime":"09:00","endTime":"11:50","bldg":"LI","room":"1305","section":"T01","web":false},{"crn":"10768","day":2,"startTime":"09:00","endTime":"11:50","bldg":"LI","room":"2310","section":"T02","web":false},{"crn":"10769","day":1,"startTime":"09:00","endTime":"11:50","bldg":"LI","room":"1305","section":"T03","web":false},{"crn":"10770","day":4,"startTime":"09:00","endTime":"11:50","bldg":"LI","room":"1305","section":"T04","web":false},{"crn":"12409","day":3,"startTime":"09:00","endTime":"11:50","bldg":"LI","room":"1102","section":"T05","web":false},{"crn":"11012","day":2,"startTime":"14:00","endTime":"16:50","bldg":"LAU","room":"5-207","section":"T06","web":false},{"crn":"12073","day":1,"startTime":"13:00","endTime":"15:50","bldg":"LI","room":"2312","section":"T07","web":false}]},"A":{"restrictions":["only for College: CB, CH, FL, SM"],"activities":[{"crn":"11323","day":5,"startTime":"09:00","endTime":"11:50","bldg":"LI","room":"1305","section":"TA1","web":false},{"crn":"11324","day":2,"startTime":"09:00","endTime":"11:50","bldg":"LI","room":"2310","section":"TA2","web":false},{"crn":"11325","day":1,"startTime":"09:00","endTime":"11:50","bldg":"LI","room":"1305","section":"TA3","web":false},{"crn":"11326","day":4,"startTime":"09:00","endTime":"11:50","bldg":"LI","room":"1305","section":"TA4","web":false},{"crn":"12410","day":3,"startTime":"09:00","endTime":"11:50","bldg":"LI","room":"1102","section":"TA5","web":false},{"crn":"11530","day":2,"startTime":"14:00","endTime":"16:50","bldg":"LAU","room":"5-207","section":"TA6","web":false},{"crn":"12075","day":1,"startTime":"13:00","endTime":"15:50","bldg":"LI","room":"2312","section":"TA7","web":false}]}}}