{"subjectCode":"SS","courseCode":"SS3707","courseTitle":"Design and Analysis for Psychological Research I","creditUnits":"3","courseLevel":["B"],"sections":{"0":{"restrictions":["only for Major: PSY"],"activities":[{"crn":"10664","day":5,"startTime":"12:00","endTime":"14:50","bldg":"LI","room":"4412","section":"C01","web":true},{"crn":"10664","day":5,"startTime":"12:00","endTime":"14:50","bldg":"LI","room":"4412","section":"C01","web":true},{"crn":"10664","day":5,"startTime":"12:00","endTime":"14:50","bldg":"LI","room":"4412","section":"C01","web":true},{"crn":"10664","day":5,"startTime":"12:00","endTime":"14:50","bldg":"LI","room":"4412","section":"C01","web":true},{"crn":"10664","day":5,"startTime":"12:00","endTime":"14:50","bldg":"LI","room":"4412","section":"C01","web":true},{"crn":"10665","day":5,"startTime":"12:00","endTime":"14:50","bldg":"LI","room":"4208","section":"T01","web":true},{"crn":"10665","day":5,"startTime":"12:00","endTime":"14:50","bldg":"LI","room":"4208","section":"T01","web":true},{"crn":"10665","day":5,"startTime":"12:00","endTime":"14:50","bldg":"LI","room":"4208","section":"T01","web":true},{"crn":"10665","day":5,"startTime":"12:00","endTime":"14:50","bldg":"LI","room":"4208","section":"T01","web":true},{"crn":"10666","day":5,"startTime":"12:00","endTime":"14:50","bldg":"LI","room":"4109","section":"T02","web":true},{"crn":"10666","day":5,"startTime":"12:00","endTime":"14:50","bldg":"LI","room":"4109","section":"T02","web":true},{"crn":"10666","day":5,"startTime":"12:00","endTime":"14:50","bldg":"LI","room":"4109","section":"T02","web":true},{"crn":"10666","day":5,"startTime":"12:00","endTime":"14:50","bldg":"LI","room":"4109","section":"T02","web":true}]}}}